zmtools/__init__.py
zmtools/api.py
zmtools-3.0.1.dist-info/LICENSE
zmtools-3.0.1.dist-info/METADATA
zmtools-3.0.1.dist-info/WHEEL
zmtools-3.0.1.dist-info/RECORD
